<profile>

<ReportVersion>
<Version>2019.2</Version>
</ReportVersion>

<UserAssignments>
<unit>ns</unit>
<ProductFamily>zynq</ProductFamily>
<Part>xc7z020-clg484-1</Part>
<TopModelName>Filter2D</TopModelName>
<TargetClockPeriod>10.00</TargetClockPeriod>
<ClockUncertainty>1.25</ClockUncertainty>
</UserAssignments>

<PerformanceEstimates>
<PipelineType>none</PipelineType>
<SummaryOfTimingAnalysis>
<unit>ns</unit>
<EstimatedClockPeriod>9.400</EstimatedClockPeriod>
</SummaryOfTimingAnalysis>
<SummaryOfOverallLatency>
<unit>clock cycles</unit>
<Best-caseLatency>202</Best-caseLatency>
<Average-caseLatency>undef</Average-caseLatency>
<Worst-caseLatency>317194</Worst-caseLatency>
<Best-caseRealTimeLatency>2.020 us</Best-caseRealTimeLatency>
<Average-caseRealTimeLatency>undef</Average-caseRealTimeLatency>
<Worst-caseRealTimeLatency>3.172 ms</Worst-caseRealTimeLatency>
<Interval-min>202</Interval-min>
<Interval-max>317194</Interval-max>
</SummaryOfOverallLatency>
<SummaryOfLoopLatency>
<Loop1>
<TripCount>3</TripCount>
<Latency>2</Latency>
<IterationLatency>1</IterationLatency>
</Loop1>
<loop_height>
<TripCount>
<range>
<min>9</min>
<max>485</max>
</range>
</TripCount>
<Latency>
<range>
<min>198</min>
<max>317190</max>
</range>
</Latency>
<IterationLatency>
<range>
<min>22</min>
<max>654</max>
</range>
</IterationLatency>
<loop_width>
<TripCount>
<range>
<min>12</min>
<max>644</max>
</range>
</TripCount>
<Latency>
<range>
<min>19</min>
<max>651</max>
</range>
</Latency>
<PipelineII>1</PipelineII>
<PipelineDepth>9</PipelineDepth>
</loop_width>
</loop_height>
</SummaryOfLoopLatency>
</PerformanceEstimates>

<AreaEstimates>
<Resources>
<BRAM_18K>15</BRAM_18K>
<DSP48E>57</DSP48E>
<FF>3137</FF>
<LUT>4769</LUT>
<URAM>0</URAM>
</Resources>
<AvailableResources>
<BRAM_18K>280</BRAM_18K>
<DSP48E>220</DSP48E>
<FF>106400</FF>
<LUT>53200</LUT>
<URAM>0</URAM>
</AvailableResources>
</AreaEstimates>

<InterfaceSummary>
<RtlPorts>
<name>ap_clk</name>
<Object>Filter2D</Object>
<Type>return value</Type>
<Scope></Scope>
<IOProtocol>ap_ctrl_hs</IOProtocol>
<IOConfig></IOConfig>
<Dir>in</Dir>
<Bits>1</Bits>
<Attribute>control</Attribute>
</RtlPorts>
<RtlPorts>
<name>ap_rst</name>
<Object>Filter2D</Object>
<Type>return value</Type>
<Scope></Scope>
<IOProtocol>ap_ctrl_hs</IOProtocol>
<IOConfig></IOConfig>
<Dir>in</Dir>
<Bits>1</Bits>
<Attribute>control</Attribute>
</RtlPorts>
<RtlPorts>
<name>ap_start</name>
<Object>Filter2D</Object>
<Type>return value</Type>
<Scope></Scope>
<IOProtocol>ap_ctrl_hs</IOProtocol>
<IOConfig></IOConfig>
<Dir>in</Dir>
<Bits>1</Bits>
<Attribute>control</Attribute>
</RtlPorts>
<RtlPorts>
<name>ap_done</name>
<Object>Filter2D</Object>
<Type>return value</Type>
<Scope></Scope>
<IOProtocol>ap_ctrl_hs</IOProtocol>
<IOConfig></IOConfig>
<Dir>out</Dir>
<Bits>1</Bits>
<Attribute>control</Attribute>
</RtlPorts>
<RtlPorts>
<name>ap_idle</name>
<Object>Filter2D</Object>
<Type>return value</Type>
<Scope></Scope>
<IOProtocol>ap_ctrl_hs</IOProtocol>
<IOConfig></IOConfig>
<Dir>out</Dir>
<Bits>1</Bits>
<Attribute>control</Attribute>
</RtlPorts>
<RtlPorts>
<name>ap_ready</name>
<Object>Filter2D</Object>
<Type>return value</Type>
<Scope></Scope>
<IOProtocol>ap_ctrl_hs</IOProtocol>
<IOConfig></IOConfig>
<Dir>out</Dir>
<Bits>1</Bits>
<Attribute>control</Attribute>
</RtlPorts>
<RtlPorts>
<name>p_src_rows_V_read</name>
<Object>p_src_rows_V_read</Object>
<Type>scalar</Type>
<Scope></Scope>
<IOProtocol>ap_none</IOProtocol>
<IOConfig></IOConfig>
<Dir>in</Dir>
<Bits>10</Bits>
<Attribute>data</Attribute>
</RtlPorts>
<RtlPorts>
<name>p_src_cols_V_read</name>
<Object>p_src_cols_V_read</Object>
<Type>scalar</Type>
<Scope></Scope>
<IOProtocol>ap_none</IOProtocol>
<IOConfig></IOConfig>
<Dir>in</Dir>
<Bits>11</Bits>
<Attribute>data</Attribute>
</RtlPorts>
<RtlPorts>
<name>p_src_data_stream_0_V_dout</name>
<Object>p_src_data_stream_0_V</Object>
<Type>pointer</Type>
<Scope></Scope>
<IOProtocol>ap_fifo</IOProtocol>
<IOConfig></IOConfig>
<Dir>in</Dir>
<Bits>8</Bits>
<Attribute>control</Attribute>
</RtlPorts>
<RtlPorts>
<name>p_src_data_stream_0_V_empty_n</name>
<Object>p_src_data_stream_0_V</Object>
<Type>pointer</Type>
<Scope></Scope>
<IOProtocol>ap_fifo</IOProtocol>
<IOConfig></IOConfig>
<Dir>in</Dir>
<Bits>1</Bits>
<Attribute>control</Attribute>
</RtlPorts>
<RtlPorts>
<name>p_src_data_stream_0_V_read</name>
<Object>p_src_data_stream_0_V</Object>
<Type>pointer</Type>
<Scope></Scope>
<IOProtocol>ap_fifo</IOProtocol>
<IOConfig></IOConfig>
<Dir>out</Dir>
<Bits>1</Bits>
<Attribute>control</Attribute>
</RtlPorts>
<RtlPorts>
<name>p_src_data_stream_1_V_dout</name>
<Object>p_src_data_stream_1_V</Object>
<Type>pointer</Type>
<Scope></Scope>
<IOProtocol>ap_fifo</IOProtocol>
<IOConfig></IOConfig>
<Dir>in</Dir>
<Bits>8</Bits>
<Attribute>control</Attribute>
</RtlPorts>
<RtlPorts>
<name>p_src_data_stream_1_V_empty_n</name>
<Object>p_src_data_stream_1_V</Object>
<Type>pointer</Type>
<Scope></Scope>
<IOProtocol>ap_fifo</IOProtocol>
<IOConfig></IOConfig>
<Dir>in</Dir>
<Bits>1</Bits>
<Attribute>control</Attribute>
</RtlPorts>
<RtlPorts>
<name>p_src_data_stream_1_V_read</name>
<Object>p_src_data_stream_1_V</Object>
<Type>pointer</Type>
<Scope></Scope>
<IOProtocol>ap_fifo</IOProtocol>
<IOConfig></IOConfig>
<Dir>out</Dir>
<Bits>1</Bits>
<Attribute>control</Attribute>
</RtlPorts>
<RtlPorts>
<name>p_src_data_stream_2_V_dout</name>
<Object>p_src_data_stream_2_V</Object>
<Type>pointer</Type>
<Scope></Scope>
<IOProtocol>ap_fifo</IOProtocol>
<IOConfig></IOConfig>
<Dir>in</Dir>
<Bits>8</Bits>
<Attribute>control</Attribute>
</RtlPorts>
<RtlPorts>
<name>p_src_data_stream_2_V_empty_n</name>
<Object>p_src_data_stream_2_V</Object>
<Type>pointer</Type>
<Scope></Scope>
<IOProtocol>ap_fifo</IOProtocol>
<IOConfig></IOConfig>
<Dir>in</Dir>
<Bits>1</Bits>
<Attribute>control</Attribute>
</RtlPorts>
<RtlPorts>
<name>p_src_data_stream_2_V_read</name>
<Object>p_src_data_stream_2_V</Object>
<Type>pointer</Type>
<Scope></Scope>
<IOProtocol>ap_fifo</IOProtocol>
<IOConfig></IOConfig>
<Dir>out</Dir>
<Bits>1</Bits>
<Attribute>control</Attribute>
</RtlPorts>
<RtlPorts>
<name>p_dst_data_stream_0_V_din</name>
<Object>p_dst_data_stream_0_V</Object>
<Type>pointer</Type>
<Scope></Scope>
<IOProtocol>ap_fifo</IOProtocol>
<IOConfig></IOConfig>
<Dir>out</Dir>
<Bits>8</Bits>
<Attribute>control</Attribute>
</RtlPorts>
<RtlPorts>
<name>p_dst_data_stream_0_V_full_n</name>
<Object>p_dst_data_stream_0_V</Object>
<Type>pointer</Type>
<Scope></Scope>
<IOProtocol>ap_fifo</IOProtocol>
<IOConfig></IOConfig>
<Dir>in</Dir>
<Bits>1</Bits>
<Attribute>control</Attribute>
</RtlPorts>
<RtlPorts>
<name>p_dst_data_stream_0_V_write</name>
<Object>p_dst_data_stream_0_V</Object>
<Type>pointer</Type>
<Scope></Scope>
<IOProtocol>ap_fifo</IOProtocol>
<IOConfig></IOConfig>
<Dir>out</Dir>
<Bits>1</Bits>
<Attribute>control</Attribute>
</RtlPorts>
<RtlPorts>
<name>p_dst_data_stream_1_V_din</name>
<Object>p_dst_data_stream_1_V</Object>
<Type>pointer</Type>
<Scope></Scope>
<IOProtocol>ap_fifo</IOProtocol>
<IOConfig></IOConfig>
<Dir>out</Dir>
<Bits>8</Bits>
<Attribute>control</Attribute>
</RtlPorts>
<RtlPorts>
<name>p_dst_data_stream_1_V_full_n</name>
<Object>p_dst_data_stream_1_V</Object>
<Type>pointer</Type>
<Scope></Scope>
<IOProtocol>ap_fifo</IOProtocol>
<IOConfig></IOConfig>
<Dir>in</Dir>
<Bits>1</Bits>
<Attribute>control</Attribute>
</RtlPorts>
<RtlPorts>
<name>p_dst_data_stream_1_V_write</name>
<Object>p_dst_data_stream_1_V</Object>
<Type>pointer</Type>
<Scope></Scope>
<IOProtocol>ap_fifo</IOProtocol>
<IOConfig></IOConfig>
<Dir>out</Dir>
<Bits>1</Bits>
<Attribute>control</Attribute>
</RtlPorts>
<RtlPorts>
<name>p_dst_data_stream_2_V_din</name>
<Object>p_dst_data_stream_2_V</Object>
<Type>pointer</Type>
<Scope></Scope>
<IOProtocol>ap_fifo</IOProtocol>
<IOConfig></IOConfig>
<Dir>out</Dir>
<Bits>8</Bits>
<Attribute>control</Attribute>
</RtlPorts>
<RtlPorts>
<name>p_dst_data_stream_2_V_full_n</name>
<Object>p_dst_data_stream_2_V</Object>
<Type>pointer</Type>
<Scope></Scope>
<IOProtocol>ap_fifo</IOProtocol>
<IOConfig></IOConfig>
<Dir>in</Dir>
<Bits>1</Bits>
<Attribute>control</Attribute>
</RtlPorts>
<RtlPorts>
<name>p_dst_data_stream_2_V_write</name>
<Object>p_dst_data_stream_2_V</Object>
<Type>pointer</Type>
<Scope></Scope>
<IOProtocol>ap_fifo</IOProtocol>
<IOConfig></IOConfig>
<Dir>out</Dir>
<Bits>1</Bits>
<Attribute>control</Attribute>
</RtlPorts>
</InterfaceSummary>

</profile>
